firebase_data/__init__.py
firebase_data/main.py
firebase_data-1.0.5.data/data/README.md
firebase_data-1.0.5.dist-info/LICENSE
firebase_data-1.0.5.dist-info/METADATA
firebase_data-1.0.5.dist-info/WHEEL
firebase_data-1.0.5.dist-info/entry_points.txt
firebase_data-1.0.5.dist-info/top_level.txt
firebase_data-1.0.5.dist-info/RECORD
