Metadata-Version: 2.1
Name: firebase-data
Version: 1.0.5
Summary: Easily transfer data between firebase projects
Home-page: https://github.com/louis030195/firebase-data
Author: Louis Beaumont
Author-email: louis.beaumont@gmail.com
License: MIT
Keywords: firebase,cloud
Platform: UNKNOWN
Classifier: Development Status :: 4 - Beta
Classifier: Intended Audience :: Developers
Classifier: Topic :: Scientific/Engineering
Classifier: License :: OSI Approved :: MIT License
Classifier: Programming Language :: Python :: 3.6
License-File: LICENSE
Requires-Dist: tqdm
Requires-Dist: firebase-admin
Requires-Dist: fire
